tno/quantum/problems/portfolio_optimization/__init__.py
tno/quantum/problems/portfolio_optimization/_portfolio_optimizer.py
tno/quantum/problems/portfolio_optimization/py.typed
tno/quantum/problems/portfolio_optimization/_components/__init__.py
tno/quantum/problems/portfolio_optimization/_components/_io.py
tno/quantum/problems/portfolio_optimization/_components/_postprocess.py
tno/quantum/problems/portfolio_optimization/_components/_results.py
tno/quantum/problems/portfolio_optimization/_components/_visualization.py
tno/quantum/problems/portfolio_optimization/_components/qubos/__init__.py
tno/quantum/problems/portfolio_optimization/_components/qubos/_qubo_compiler.py
tno/quantum/problems/portfolio_optimization/_components/qubos/_qubo_factory.py
tno/quantum/problems/portfolio_optimization/assets/example.png
tno/quantum/problems/portfolio_optimization/datasets/benchmark_dataset.xlsx
tno/quantum/problems/portfolio_optimization/test/__init__.py
tno/quantum/problems/portfolio_optimization/test/dataset_for_tests.py
tno/quantum/problems/portfolio_optimization/test/test_portfolio_optimizer.py
tno/quantum/problems/portfolio_optimization/test/components/__init__.py
tno/quantum/problems/portfolio_optimization/test/components/io.py
tno/quantum/problems/portfolio_optimization/test/components/test_postprocess.py
tno/quantum/problems/portfolio_optimization/test/components/test_results.py
tno/quantum/problems/portfolio_optimization/test/components/qubos/test_qubo_compiler.py
tno/quantum/problems/portfolio_optimization/test/components/qubos/test_qubo_factory.py
tno_quantum_problems_portfolio_optimization-2.0.0.dist-info/licenses/LICENSE
tno_quantum_problems_portfolio_optimization-2.0.0.dist-info/METADATA
tno_quantum_problems_portfolio_optimization-2.0.0.dist-info/WHEEL
tno_quantum_problems_portfolio_optimization-2.0.0.dist-info/top_level.txt
tno_quantum_problems_portfolio_optimization-2.0.0.dist-info/RECORD
